{
  "openapi": "3.0.4",
  "info": {
    "title": "Directory Service API",
    "description": "API для тестирования backend логики",
    "version": "v1"
  },
  "paths": {
    "/api/locations": {
      "get": {
        "tags": [
          "Locations"
        ],
        "responses": {
          "200": {
            "description": "OK"
          }
        }
      },
      "post": {
        "tags": [
          "Locations"
        ],
        "requestBody": {
          "content": {
            "application/json": {
              "schema": {
                "$ref": "#/components/schemas/CreateLocationRequest"
              }
            },
            "text/json": {
              "schema": {
                "$ref": "#/components/schemas/CreateLocationRequest"
              }
            },
            "application/*+json": {
              "schema": {
                "$ref": "#/components/schemas/CreateLocationRequest"
              }
            }
          }
        },
        "responses": {
          "200": {
            "description": "OK"
          }
        }
      }
    },
    "/api/locations/{id}": {
      "get": {
        "tags": [
          "Locations"
        ],
        "parameters": [
          {
            "name": "id",
            "in": "path",
            "required": true,
            "schema": {
              "type": "string",
              "format": "uuid"
            }
          }
        ],
        "responses": {
          "200": {
            "description": "OK"
          }
        }
      },
      "patch": {
        "tags": [
          "Locations"
        ],
        "parameters": [
          {
            "name": "id",
            "in": "path",
            "required": true,
            "schema": {
              "type": "string",
              "format": "uuid"
            }
          }
        ],
        "requestBody": {
          "content": {
            "application/json": {
              "schema": {
                "$ref": "#/components/schemas/UpdateLocationRequest"
              }
            },
            "text/json": {
              "schema": {
                "$ref": "#/components/schemas/UpdateLocationRequest"
              }
            },
            "application/*+json": {
              "schema": {
                "$ref": "#/components/schemas/UpdateLocationRequest"
              }
            }
          }
        },
        "responses": {
          "200": {
            "description": "OK"
          }
        }
      },
      "delete": {
        "tags": [
          "Locations"
        ],
        "parameters": [
          {
            "name": "id",
            "in": "path",
            "required": true,
            "schema": {
              "type": "string",
              "format": "uuid"
            }
          }
        ],
        "responses": {
          "200": {
            "description": "OK"
          }
        }
      }
    },
    "/api/locations/{id}/hard": {
      "delete": {
        "tags": [
          "Locations"
        ],
        "parameters": [
          {
            "name": "id",
            "in": "path",
            "required": true,
            "schema": {
              "type": "string",
              "format": "uuid"
            }
          }
        ],
        "responses": {
          "200": {
            "description": "OK"
          }
        }
      }
    },
    "/api/positions": {
      "get": {
        "tags": [
          "Positions"
        ],
        "responses": {
          "200": {
            "description": "OK"
          }
        }
      },
      "post": {
        "tags": [
          "Positions"
        ],
        "requestBody": {
          "content": {
            "application/json": {
              "schema": {
                "$ref": "#/components/schemas/CreatePositionRequest"
              }
            },
            "text/json": {
              "schema": {
                "$ref": "#/components/schemas/CreatePositionRequest"
              }
            },
            "application/*+json": {
              "schema": {
                "$ref": "#/components/schemas/CreatePositionRequest"
              }
            }
          }
        },
        "responses": {
          "200": {
            "description": "OK"
          }
        }
      }
    },
    "/api/positions/{id}": {
      "get": {
        "tags": [
          "Positions"
        ],
        "parameters": [
          {
            "name": "id",
            "in": "path",
            "required": true,
            "schema": {
              "type": "string",
              "format": "uuid"
            }
          }
        ],
        "responses": {
          "200": {
            "description": "OK"
          }
        }
      },
      "patch": {
        "tags": [
          "Positions"
        ],
        "parameters": [
          {
            "name": "id",
            "in": "path",
            "required": true,
            "schema": {
              "type": "string",
              "format": "uuid"
            }
          }
        ],
        "requestBody": {
          "content": {
            "application/json": {
              "schema": {
                "$ref": "#/components/schemas/UpdatePositionRequest"
              }
            },
            "text/json": {
              "schema": {
                "$ref": "#/components/schemas/UpdatePositionRequest"
              }
            },
            "application/*+json": {
              "schema": {
                "$ref": "#/components/schemas/UpdatePositionRequest"
              }
            }
          }
        },
        "responses": {
          "200": {
            "description": "OK"
          }
        }
      },
      "delete": {
        "tags": [
          "Positions"
        ],
        "parameters": [
          {
            "name": "id",
            "in": "path",
            "required": true,
            "schema": {
              "type": "string",
              "format": "uuid"
            }
          }
        ],
        "responses": {
          "200": {
            "description": "OK"
          }
        }
      }
    },
    "/api/positions/{id}/hard": {
      "delete": {
        "tags": [
          "Positions"
        ],
        "parameters": [
          {
            "name": "id",
            "in": "path",
            "required": true,
            "schema": {
              "type": "string",
              "format": "uuid"
            }
          }
        ],
        "responses": {
          "200": {
            "description": "OK"
          }
        }
      }
    }
  },
  "components": {
    "schemas": {
      "CreateLocationRequest": {
        "type": "object",
        "properties": {
          "address": {
            "type": "string",
            "nullable": true
          },
          "name": {
            "type": "string",
            "nullable": true
          },
          "timeZone": {
            "type": "string",
            "nullable": true
          }
        },
        "additionalProperties": false
      },
      "CreatePositionRequest": {
        "type": "object",
        "properties": {
          "name": {
            "type": "string",
            "nullable": true
          },
          "description": {
            "type": "string",
            "nullable": true
          },
          "isActive": {
            "type": "boolean"
          }
        },
        "additionalProperties": false
      },
      "UpdateLocationRequest": {
        "type": "object",
        "properties": {
          "address": {
            "type": "string",
            "nullable": true
          },
          "name": {
            "type": "string",
            "nullable": true
          },
          "timeZone": {
            "type": "string",
            "nullable": true
          }
        },
        "additionalProperties": false
      },
      "UpdatePositionRequest": {
        "type": "object",
        "properties": {
          "name": {
            "type": "string",
            "nullable": true
          },
          "description": {
            "type": "string",
            "nullable": true
          },
          "isActive": {
            "type": "boolean",
            "nullable": true
          }
        },
        "additionalProperties": false
      }
    }
  },
  "tags": [
    {
      "name": "Locations"
    },
    {
      "name": "Positions"
    }
  ]
}